[
  {
    "package": "effectsize",
    "url": "https://github.com/easystats/effectsize",
    "via": ["report"],
    "from": "report"
  },
  {
    "package": "emmeans",
    "url": "https://github.com/rvlenth/emmeans",
    "via": ["bayestestR"],
    "from": "bayestestR"
  },
  {
    "package": "insight",
    "url": "https://github.com/easystats/insight",
    "via": ["bayestestR"],
    "from": "bayestestR"
  },
  {
    "package": "insight",
    "url": "https://github.com/easystats/insight",
    "via": ["correlation"],
    "from": "correlation"
  },
  {
    "package": "insight",
    "url": "https://github.com/easystats/insight",
    "via": ["datawizard"],
    "from": "datawizard"
  },
  {
    "package": "insight",
    "url": "https://github.com/easystats/insight",
    "via": ["easystats"],
    "from": "easystats"
  },
  {
    "package": "insight",
    "url": "https://github.com/easystats/insight",
    "via": ["effectsize"],
    "from": "effectsize"
  },
  {
    "package": "insight",
    "url": "https://github.com/easystats/insight",
    "via": ["modelbased"],
    "from": "modelbased"
  },
  {
    "package": "insight",
    "url": "https://github.com/easystats/insight",
    "via": ["report"],
    "from": "report"
  },
  {
    "package": "insight",
    "url": "https://github.com/easystats/insight",
    "via": ["see"],
    "from": "see"
  }
]
